VERILOG/Manchester/manch_mod.v
/*------------------------------------------------------------------------
--                     Codificador Manchester                     	--
-- * 1.0                                                          	--
-- Descripcion:                                                   	--
--    	Codificador manchester 		                          	--
--Ingresa el frame a enviar y sale codificado (codificacion manchester) --
--	Test bench de este archivo en tb_manch_mod.v			--
------------------------------------------------------------------------*/

module man_mod #(parameter N = 3)(clk, in_enable, in_data, out_data);

input clk;		//Clock de fc/16 en RFID (847,5 KHz)
input in_data;		//Informacion - ETU de 106Kb/s (8 clocks dentro de cada ETU)
input in_enable;	//Bit de habilitacion del modulo
output reg out_data;	//Salida del codificador manchester

reg  [N-1:0] count;	//Cuento los cuatro clock para estar en la mitad del ETU
reg etu;		//0 si se está en la primer mitad del etu - 1 si se está en la segunda mitad

always @ (negedge clk, negedge in_enable) begin
    if(~in_enable) begin	//Cuando esta desabilitado el modulo, pongo la salida y el contador en 0 (cero)
    out_data <= 1'b0;
    etu <= 1'b0;
    count <= {N{1'b0}};
    end 
    else begin
        count <= count +1;
        if(count == 3'b100) begin	//Cuando cuento la mitad de los clocks que entran en un etu
            etu = ~ etu;		//invierto el etu
            count <= 3'b001;	//reseteo el contador
        end
        if(~etu) begin		//Si estoy en la primera mitad del ETU
            if(in_data) begin	//Si estoy en presencia de un 1 como dato
                out_data <= clk;	//Copio el clk
            end 
            else begin 		//Si estoy en presencia de un 0 como dato
                out_data <= 1'b1;	//Pongo en 1 la salida
            end
        end 
        else begin		//Si estoy en la segunda mitad de ETU
            if(~in_data) begin	//Si estoy en presencia de un 0 como dato
                out_data <= clk;	//Copio el clk
            end
            else begin 		//Si estoy en presencia de un 1 como dato
                out_data <= 1'b1;	//Pongo en 1 la salida
            end
        end	
    end
end
	 	    
always @ (posedge clk, negedge in_enable) begin
    if(~in_enable) begin	//Cuando esta desabilitado el modulo, pongo la salida y el contador en 0 (cero)
        out_data <= 1'b0;
        etu <= 1'b0;
        count <= {N{1'b0}};
    end
    else begin
        if(~etu) begin		//Si estoy en la primera mitad del ETU
            if(in_data) begin	//Si estoy en presencia de un 1 como dato
                out_data <= clk;	//Copio el clk
            end 
            else begin 		//Si estoy en presencia de un 0 como dato
                out_data <= 1'b1;	//Pongo en 1 la salida
            end
        end
        else begin		//Si estoy en la segunda mitad de ETU
            if(~in_data) begin	//Si estoy en presencia de un 0 como dato
                out_data <= clk;	//Copio el clk
            end
        end
    end
end

endmodule

VERILOG/Manchester/tb_manch_mod.v
/*----------------------------------------------------------------
--          Test Bench						--
-- Archivo a testear: 	manch_mod.v				--
-- Descripcion:		DUT codificador manchester		--
----------------------------------------------------------------*/

 `timescale 1us/1us	//Dividir el eje de tiempo en unidades de 1us

module man_mod_tb;	//Modulo de test bench

// Entradas del DUT son reg
  reg clk;
  reg in_data;
  reg in_enable;
//   Las salidas del DUT son wire
  wire out_data;
  
  man_mod u1(clk, in_enable, in_data, out_data);	//DUT a testear
//----------------------------------------------------------
// Inicializo
// Inicializar todo para que no quede en estados "fantasmas"
    initial
    begin
      clk= 1'b0; 
      in_data= 1'b0;
      in_enable=1'b0; 

      end
//----------------------------------------------------------
// Creo un clock de 500khz
    always
      #1 clk = ~clk;   // Cada 1 us invierto
	 
//-----------------------------------------------------------

    initial
      begin
//      forever #10 clk = ~clk; // generate a clock	
	#10 repeat(4) #8 in_data = ~in_data;		//10us del arranque, switcheo in_data cada 8us
	#36 in_enable=1'b1; 				//36us despues de la instruccion anterior habilito el dispositivo
	#16 repeat(4) #16 in_data = ~in_data;		//16us despues de la instruccion anterior switcheo in_data cada 24us
	in_data=1'b0;					//Pongo a 0 in_data
	#16	in_data = 1'b1;				//16us despues, lo pngo a 1

// 	#16 in_enable=1'b0; 	
// 	#32 in_enable=1'b1; 
//  	#560 repeat(10) #10 in_data = ~in_data;
	#32 in_enable=1'b0; 				//Deshabilito el dispositivo
	#16 $finish;					//Finalizo la simulación
      end
 
//     initial	
//       $monitor("clk=%b,in_data=%b,in_enable=%b",clk,in_data,in_enable);	//Imprimo en consola los datos
 
    initial
    begin
      $dumpfile("man_mod_tb.vcd");	//Creo el archivo para simular con GTKWave
      $dumpvars(0, man_mod_tb);
    end
endmodule

VERILOG/Manchester/man_mod_tb.vcd
$date
	Sat Mar 25 18:43:38 2017
$end
$version
	Icarus Verilog
$end
$timescale
	1us
$end
$scope module man_mod_tb $end
$var wire 1 ! out_data $end
$var reg 1 " clk $end
$var reg 1 # in_data $end
$var reg 1 $ in_enable $end
$scope module u1 $end
$var wire 1 % clk $end
$var wire 1 & in_data $end
$var wire 1 ' in_enable $end
$var reg 3 ( count [2:0] $end
$var reg 1 ) etu $end
$var reg 1 * out_data $end
$upscope $end
$upscope $end
$enddefinitions $end
#0
$dumpvars
0*
0)
b0 (
0'
0&
0%
0$
0#
0"
0!
$end
#1
1"
1%
#2
0"
0%
#3
1"
1%
#4
0"
0%
#5
1"
1%
#6
0"
0%
#7
1"
1%
#8
0"
0%
#9
1"
1%
#10
0"
0%
#11
1"
1%
#12
0"
0%
#13
1"
1%
#14
0"
0%
#15
1"
1%
#16
0"
0%
#17
1"
1%
#18
0"
0%
1#
1&
#19
1"
1%
#20
0"
0%
#21
1"
1%
#22
0"
0%
#23
1"
1%
#24
0"
0%
#25
1"
1%
#26
0"
0%
0#
0&
#27
1"
1%
#28
0"
0%
#29
1"
1%
#30
0"
0%
#31
1"
1%
#32
0"
0%
#33
1"
1%
#34
0"
0%
1#
1&
#35
1"
1%
#36
0"
0%
#37
1"
1%
#38
0"
0%
#39
1"
1%
#40
0"
0%
#41
1"
1%
#42
0"
0%
0#
0&
#43
1"
1%
#44
0"
0%
#45
1"
1%
#46
0"
0%
#47
1"
1%
#48
0"
0%
#49
1"
1%
#50
0"
0%
#51
1"
1%
#52
0"
0%
#53
1"
1%
#54
0"
0%
#55
1"
1%
#56
0"
0%
#57
1"
1%
#58
0"
0%
#59
1"
1%
#60
0"
0%
#61
1"
1%
#62
0"
0%
#63
1"
1%
#64
0"
0%
#65
1"
1%
#66
0"
0%
#67
1"
1%
#68
0"
0%
#69
1"
1%
#70
0"
0%
#71
1"
1%
#72
0"
0%
#73
1"
1%
#74
0"
0%
#75
1"
1%
#76
0"
0%
#77
1"
1%
#78
1*
1!
b1 (
0"
0%
1$
1'
#79
1"
1%
#80
b10 (
0"
0%
#81
1"
1%
#82
b11 (
0"
0%
#83
1"
1%
#84
b100 (
0"
0%
#85
1"
1%
#86
0*
0!
b1 (
1)
0"
0%
#87
1*
1!
1"
1%
#88
0*
0!
b10 (
0"
0%
#89
1*
1!
1"
1%
#90
0*
0!
b11 (
0"
0%
#91
1*
1!
1"
1%
#92
0*
0!
b100 (
0"
0%
#93
1*
1!
1"
1%
#94
b1 (
0)
0"
0%
#95
1"
1%
#96
b10 (
0"
0%
#97
1"
1%
#98
b11 (
0"
0%
#99
1"
1%
#100
b100 (
0"
0%
#101
1"
1%
#102
0*
0!
b1 (
1)
0"
0%
#103
1*
1!
1"
1%
#104
0*
0!
b10 (
0"
0%
#105
1*
1!
1"
1%
#106
0*
0!
b11 (
0"
0%
#107
1*
1!
1"
1%
#108
0*
0!
b100 (
0"
0%
#109
1*
1!
1"
1%
#110
0*
0!
b1 (
0)
0"
0%
1#
1&
#111
1*
1!
1"
1%
#112
0*
0!
b10 (
0"
0%
#113
1*
1!
1"
1%
#114
0*
0!
b11 (
0"
0%
#115
1*
1!
1"
1%
#116
0*
0!
b100 (
0"
0%
#117
1*
1!
1"
1%
#118
b1 (
1)
0"
0%
#119
1"
1%
#120
b10 (
0"
0%
#121
1"
1%
#122
b11 (
0"
0%
#123
1"
1%
#124
b100 (
0"
0%
#125
1"
1%
#126
b1 (
0)
0"
0%
0#
0&
#127
1"
1%
#128
b10 (
0"
0%
#129
1"
1%
#130
b11 (
0"
0%
#131
1"
1%
#132
b100 (
0"
0%
#133
1"
1%
#134
0*
0!
b1 (
1)
0"
0%
#135
1*
1!
1"
1%
#136
0*
0!
b10 (
0"
0%
#137
1*
1!
1"
1%
#138
0*
0!
b11 (
0"
0%
#139
1*
1!
1"
1%
#140
0*
0!
b100 (
0"
0%
#141
1*
1!
1"
1%
#142
0*
0!
b1 (
0)
0"
0%
1#
1&
#143
1*
1!
1"
1%
#144
0*
0!
b10 (
0"
0%
#145
1*
1!
1"
1%
#146
0*
0!
b11 (
0"
0%
#147
1*
1!
1"
1%
#148
0*
0!
b100 (
0"
0%
#149
1*
1!
1"
1%
#150
b1 (
1)
0"
0%
#151
1"
1%
#152
b10 (
0"
0%
#153
1"
1%
#154
b11 (
0"
0%
#155
1"
1%
#156
b100 (
0"
0%
#157
1"
1%
#158
b1 (
0)
0"
0%
0#
0&
#159
1"
1%
#160
b10 (
0"
0%
#161
1"
1%
#162
b11 (
0"
0%
#163
1"
1%
#164
b100 (
0"
0%
#165
1"
1%
#166
0*
0!
b1 (
1)
0"
0%
#167
1*
1!
1"
1%
#168
0*
0!
b10 (
0"
0%
#169
1*
1!
1"
1%
#170
0*
0!
b11 (
0"
0%
#171
1*
1!
1"
1%
#172
0*
0!
b100 (
0"
0%
#173
1*
1!
1"
1%
#174
0*
0!
b1 (
0)
0"
0%
1#
1&
#175
1*
1!
1"
1%
#176
0*
0!
b10 (
0"
0%
#177
1*
1!
1"
1%
#178
0*
0!
b11 (
0"
0%
#179
1*
1!
1"
1%
#180
0*
0!
b100 (
0"
0%
#181
1*
1!
1"
1%
#182
b1 (
1)
0"
0%
#183
1"
1%
#184
b10 (
0"
0%
#185
1"
1%
#186
b11 (
0"
0%
#187
1"
1%
#188
b100 (
0"
0%
#189
1"
1%
#190
0*
0!
b1 (
0)
0"
0%
#191
1*
1!
1"
1%
#192
0*
0!
b10 (
0"
0%
#193
1*
1!
1"
1%
#194
0*
0!
b11 (
0"
0%
#195
1*
1!
1"
1%
#196
0*
0!
b100 (
0"
0%
#197
1*
1!
1"
1%
#198
b1 (
1)
0"
0%
#199
1"
1%
#200
b10 (
0"
0%
#201
1"
1%
#202
b11 (
0"
0%
#203
1"
1%
#204
b100 (
0"
0%
#205
1"
1%
#206
b0 (
0)
0*
0!
0"
0%
0$
0'
