VERILOG/Miller Modificado/SoF Detector/SoF_Detect.v
/*--------------------------------------------------------------------------------
--                     Detector del Start of Frame                 				--
-- * 1.0                                                          				--
-- Descripcion:                                                   				--
--    	SoF Detect	                          									--
--Analiza la información en Miller modificado y detecta el simbolo "Z"(SoF)	--	
--------------------------------------------------------------------------------*/

module SoF_Detect #(parameter N = 5)(in_clk, in_data, out_enable, in_pause, in_PoR, in_y_detected);

	input in_clk;			//Clock a fc/4 = 13.56MHz/4
	input in_data;			//Informacion - ETU de 106Kb/s (32 clocks dentro de cada ETU)
	input in_pause;			//Entrada que viene desde el detector de pause
	input in_PoR;			//Power On Reset
	input in_y_detected;	//Cuando el Detector de End of Frame detecta el EoF, pone en 1
	output reg out_enable;	//Cuando detecto el simbolo "Z", habilito el decodificador Miller
	
	reg  [N-1:0] reg_count;		//Cuento los clock para estar en la mitad del ETU
	reg reg_pause;			
	reg reg_flag;				//Bandera para manejar cuando detectar el simbolo "Z" y cuando mandar a dormir el modulo
	
	always @(negedge in_clk, posedge in_pause, posedge in_y_detected) begin
		if(~in_PoR) begin	//Inicializo todo	
			reg_pause <= 1'b0;
			reg_flag <= 1'b0;
			reg_count <= {N{1'b0}};		
			out_enable <= 1'b0;
		end else begin
	if(in_pause) begin		//Tomo el valor de la entrada y lo pongo en un registro
	reg_pause <= in_pause;
      end	
		if(~reg_flag) begin	//Si el flag esta en 0, busco detectar el simbolo Z
			if(reg_pause) begin
				reg_count <= reg_count +1;	//Pasó la pausa y tengo que contar medio ETU para detectar el "Z"
				if(reg_count == {N-1{1'b1}}) begin
					out_enable <= 1'b1;				//Pongo la salida en 1
					reg_flag <= 1'b1;				//Cambio el flag
				end		
			end		
		end else begin
			if(in_y_detected == 1'b1) begin
				out_enable <= 1'b0;
				reg_pause <= 1'b0;
				reg_flag <= 1'b0;
				reg_count <= {N{1'b0}};	
			end
		end
		end
	end
endmodule

VERILOG/Miller Modificado/SoF Detector/tb_SoF_Detect.v
/*----------------------------------------------------------------
--          Test Bench						                              --
-- Archivo a testear: 	SoF_Detect.v			                      --
-- Descripcion:		SoF Detect	                                  --
-- Observacion:							                                    --
--	                                                            --
----------------------------------------------------------------*/

//Frecuencia in_clk = 3.39MHz
//Frecuencia ETU = 106KHz
// Entran 32 clock's dentro de cada ETU

 `timescale 1us/1us	//Dividir el eje de tiempo en unidades de 1us

module SoF_Detect_tb;	//Modulo de test bench

// Entradas del DUT son reg
  reg in_clk;
  reg in_data;
  reg in_PoR;
  reg in_pause;
  reg in_y_detected;
//   Las salidas del DUT son wire
  wire out_enable;
  
  SoF_Detect u1(in_clk, in_data, out_enable, in_pause, in_PoR, in_y_detected);	//DUT a testear
//----------------------------------------------------------
// Inicializo
// Inicializar todo para que no quede en estados "fantasmas"
    initial
    begin
      in_PoR= 1'b0;   //Arrancando con el Power on reset en cero, hago que el DUT inicialice sus registros  
	  in_clk = 1'b0;
		in_data = 1'b0;
      end
//----------------------------------------------------------
// Creo un clock de 500khz
    always
      #1 in_clk = ~in_clk;   // Cada 1 us invierto
	 
//-----------------------------------------------------------

    initial
      begin
        
	#10 repeat(4) #8 in_data = ~in_data;		//10us del arranque, switcheo in_data cada 8us
  	#50 in_PoR = 1'b1;
// 	#16 repeat(4) #16 in_data = ~in_data;		//8us despues de la instruccion anterior switcheo in_data cada 24us
	#2in_data = 1'b1;					//Pongo a 1 in_data
	#32 in_data = ~in_data;				
	#32 in_data = ~in_data;				
	in_pause = 1'b1;
	#64 in_data = ~in_data;				
	#32 in_data = ~in_data;				
	in_pause = ~in_pause;
	in_y_detected = 1'b1;
	#4 in_y_detected = ~in_y_detected;
	#64 in_data = ~in_data;				
	#32 in_data = ~in_data;				
	in_pause = ~in_pause;
	#32 in_data = ~in_data;				
	#32 in_data = ~in_data;				
	
//  	#560 repeat(10) #10 in_data = ~in_data;
	#16 $finish;					//Finalizo la simulación
      end
 
//     initial	
//       $monitor("in_clk=%b,in_data=%b,in_enable=%b",in_clk,in_data,in_enable);	//Imprimo en consola los datos
 
    initial
    begin
      $dumpfile("SoF_Detect_tb.vcd");	//Creo el archivo para simular con GTKWave
      $dumpvars(0, SoF_Detect_tb);
    end
endmodule

VERILOG/Miller Modificado/SoF Detector/SoF_Detect_tb.vcd
$date
	Sun Apr 23 21:01:17 2017
$end
$version
	Icarus Verilog
$end
$timescale
	1us
$end
$scope module SoF_Detect_tb $end
$var wire 1 ! out_enable $end
$var reg 1 " in_PoR $end
$var reg 1 # in_clk $end
$var reg 1 $ in_data $end
$var reg 1 % in_pause $end
$var reg 1 & in_y_detected $end
$scope module u1 $end
$var wire 1 ' in_PoR $end
$var wire 1 ( in_clk $end
$var wire 1 ) in_data $end
$var wire 1 * in_pause $end
$var wire 1 + in_y_detected $end
$var reg 1 , out_enable $end
$var reg 5 - reg_count [4:0] $end
$var reg 1 . reg_flag $end
$var reg 1 / reg_pause $end
$upscope $end
$upscope $end
$enddefinitions $end
#0
$dumpvars
0/
0.
b0 -
0,
x+
x*
0)
0(
0'
x&
x%
0$
0#
0"
0!
$end
#1
1#
1(
#2
0#
0(
#3
1#
1(
#4
0#
0(
#5
1#
1(
#6
0#
0(
#7
1#
1(
#8
0#
0(
#9
1#
1(
#10
0#
0(
#11
1#
1(
#12
0#
0(
#13
1#
1(
#14
0#
0(
#15
1#
1(
#16
0#
0(
#17
1#
1(
#18
0#
0(
1$
1)
#19
1#
1(
#20
0#
0(
#21
1#
1(
#22
0#
0(
#23
1#
1(
#24
0#
0(
#25
1#
1(
#26
0#
0(
0$
0)
#27
1#
1(
#28
0#
0(
#29
1#
1(
#30
0#
0(
#31
1#
1(
#32
0#
0(
#33
1#
1(
#34
0#
0(
1$
1)
#35
1#
1(
#36
0#
0(
#37
1#
1(
#38
0#
0(
#39
1#
1(
#40
0#
0(
#41
1#
1(
#42
0#
0(
0$
0)
#43
1#
1(
#44
0#
0(
#45
1#
1(
#46
0#
0(
#47
1#
1(
#48
0#
0(
#49
1#
1(
#50
0#
0(
#51
1#
1(
#52
0#
0(
#53
1#
1(
#54
0#
0(
#55
1#
1(
#56
0#
0(
#57
1#
1(
#58
0#
0(
#59
1#
1(
#60
0#
0(
#61
1#
1(
#62
0#
0(
#63
1#
1(
#64
0#
0(
#65
1#
1(
#66
0#
0(
#67
1#
1(
#68
0#
0(
#69
1#
1(
#70
0#
0(
#71
1#
1(
#72
0#
0(
#73
1#
1(
#74
0#
0(
#75
1#
1(
#76
0#
0(
#77
1#
1(
#78
0#
0(
#79
1#
1(
#80
0#
0(
#81
1#
1(
#82
0#
0(
#83
1#
1(
#84
0#
0(
#85
1#
1(
#86
0#
0(
#87
1#
1(
#88
0#
0(
#89
1#
1(
#90
0#
0(
#91
1#
1(
#92
0#
0(
1"
1'
#93
1#
1(
#94
0#
0(
1$
1)
#95
1#
1(
#96
0#
0(
#97
1#
1(
#98
0#
0(
#99
1#
1(
#100
0#
0(
#101
1#
1(
#102
0#
0(
#103
1#
1(
#104
0#
0(
#105
1#
1(
#106
0#
0(
#107
1#
1(
#108
0#
0(
#109
1#
1(
#110
0#
0(
#111
1#
1(
#112
0#
0(
#113
1#
1(
#114
0#
0(
#115
1#
1(
#116
0#
0(
#117
1#
1(
#118
0#
0(
#119
1#
1(
#120
0#
0(
#121
1#
1(
#122
0#
0(
#123
1#
1(
#124
0#
0(
#125
1#
1(
#126
0#
0(
0$
0)
#127
1#
1(
#128
0#
0(
#129
1#
1(
#130
0#
0(
#131
1#
1(
#132
0#
0(
#133
1#
1(
#134
0#
0(
#135
1#
1(
#136
0#
0(
#137
1#
1(
#138
0#
0(
#139
1#
1(
#140
0#
0(
#141
1#
1(
#142
0#
0(
#143
1#
1(
#144
0#
0(
#145
1#
1(
#146
0#
0(
#147
1#
1(
#148
0#
0(
#149
1#
1(
#150
0#
0(
#151
1#
1(
#152
0#
0(
#153
1#
1(
#154
0#
0(
#155
1#
1(
#156
0#
0(
#157
1#
1(
#158
1/
0#
0(
1%
1*
1$
1)
#159
1#
1(
#160
b1 -
0#
0(
#161
1#
1(
#162
b10 -
0#
0(
#163
1#
1(
#164
b11 -
0#
0(
#165
1#
1(
#166
b100 -
0#
0(
#167
1#
1(
#168
b101 -
0#
0(
#169
1#
1(
#170
b110 -
0#
0(
#171
1#
1(
#172
b111 -
0#
0(
#173
1#
1(
#174
b1000 -
0#
0(
#175
1#
1(
#176
b1001 -
0#
0(
#177
1#
1(
#178
b1010 -
0#
0(
#179
1#
1(
#180
b1011 -
0#
0(
#181
1#
1(
#182
b1100 -
0#
0(
#183
1#
1(
#184
b1101 -
0#
0(
#185
1#
1(
#186
b1110 -
0#
0(
#187
1#
1(
#188
b1111 -
0#
0(
#189
1#
1(
#190
1.
1,
1!
b10000 -
0#
0(
#191
1#
1(
#192
0#
0(
#193
1#
1(
#194
0#
0(
#195
1#
1(
#196
0#
0(
#197
1#
1(
#198
0#
0(
#199
1#
1(
#200
0#
0(
#201
1#
1(
#202
0#
0(
#203
1#
1(
#204
0#
0(
#205
1#
1(
#206
0#
0(
#207
1#
1(
#208
0#
0(
#209
1#
1(
#210
0#
0(
#211
1#
1(
#212
0#
0(
#213
1#
1(
#214
0#
0(
#215
1#
1(
#216
0#
0(
#217
1#
1(
#218
0#
0(
#219
1#
1(
#220
0#
0(
#221
1#
1(
#222
0#
0(
0$
0)
#223
1#
1(
#224
0#
0(
#225
1#
1(
#226
0#
0(
#227
1#
1(
#228
0#
0(
#229
1#
1(
#230
0#
0(
#231
1#
1(
#232
0#
0(
#233
1#
1(
#234
0#
0(
#235
1#
1(
#236
0#
0(
#237
1#
1(
#238
0#
0(
#239
1#
1(
#240
0#
0(
#241
1#
1(
#242
0#
0(
#243
1#
1(
#244
0#
0(
#245
1#
1(
#246
0#
0(
#247
1#
1(
#248
0#
0(
#249
1#
1(
#250
0#
0(
#251
1#
1(
#252
0#
0(
#253
1#
1(
#254
b0 -
0.
0/
0,
0!
0#
0(
1&
1+
0%
0*
1$
1)
#255
1#
1(
#256
0#
0(
#257
1#
1(
#258
0#
0(
0&
0+
